fad.v
`timescale 1ns/1ps
module adder(a,b,ci,s,c1);
	input a,b,ci;
	output s,c1;
	wire [7:0] c;
	nand(c[1],a,b);
	nand(c[2],c[1],a);
	nand(c[3],c[1],b);
	nand(c[4],c[2],c[3]);
	nand(c[5],c[4],ci);
	nand(c[0],c[4],c[5]);
	nand(c[6],c[5],ci);
	nand(s,c[6],c[0]);
	nand(c1,c[1],c[5]);
endmodule

4b_ad.v
`timescale 1ns/1ps
`include "fad.v"
module b_fad(a,b,c,d,e);
input [3:0] a,b;
input c;
output [3:0] d;
output e;
wire [3:0] f;
adder f1(a[0],b[0],c,d[0],f[0]);
adder f2(a[1],b[1],f[0],d[1],f[1]);
adder f3(a[2],b[2],f[1],d[2],f[2]);
adder f4(a[3],b[3],f[2],d[3],e);
endmodule

4b_tes.v
`timescale 1ns/1ps
module testbench2;
	reg [3:0] a,x;
	reg c;
	wire [3:0] y;
	wire z;
	b_fad g1(a,x,c,y,z);
	initial
		begin
			$dumpfile("f4b.vcd");
			$dumpvars;
			$monitor(,$time," a=%b, x=%b,c=%b, y=%b,z=%b",a,x,c,y,z);
			#0 a=4'b1010;x=4'b1111;c=1'b0;
			#5 c=1'b1;
			#10 a=4'b0010;x=4'b1100;
			#15 c = 1'b0;
			#20 a=4'b1010;x=4'b0001;
			#25 c=1'b1;
			#30 a=4'b1010;x=4'b0011;
			#50 c=1'b0;
			#100 $finish;
		end
endmodule

f4b.vcd
$date
	Tue Aug 29 15:48:13 2017
$end
$version
	Icarus Verilog
$end
$timescale
	1ps
$end
$scope module testbench2 $end
$var wire 1 ! z $end
$var wire 4 " y [3:0] $end
$var reg 4 # a [3:0] $end
$var reg 1 $ c $end
$var reg 4 % x [3:0] $end
$scope module g1 $end
$var wire 4 & a [3:0] $end
$var wire 4 ' b [3:0] $end
$var wire 1 $ c $end
$var wire 4 ( f [3:0] $end
$var wire 1 ! e $end
$var wire 4 ) d [3:0] $end
$scope module f1 $end
$var wire 1 * a $end
$var wire 1 + b $end
$var wire 1 , c1 $end
$var wire 1 $ ci $end
$var wire 1 - s $end
$var wire 8 . c [7:0] $end
$upscope $end
$scope module f2 $end
$var wire 1 / a $end
$var wire 1 0 b $end
$var wire 1 1 c1 $end
$var wire 1 2 ci $end
$var wire 1 3 s $end
$var wire 8 4 c [7:0] $end
$upscope $end
$scope module f3 $end
$var wire 1 5 a $end
$var wire 1 6 b $end
$var wire 1 7 c1 $end
$var wire 1 8 ci $end
$var wire 1 9 s $end
$var wire 8 : c [7:0] $end
$upscope $end
$scope module f4 $end
$var wire 1 ; a $end
$var wire 1 < b $end
$var wire 1 ! c1 $end
$var wire 1 = ci $end
$var wire 1 > s $end
$var wire 8 ? c [7:0] $end
$upscope $end
$upscope $end
$upscope $end
$enddefinitions $end
#0
$dumpvars
bz0101101 ?
1>
1=
1<
1;
bz1010111 :
09
18
17
16
05
bz1101101 4
03
02
11
10
1/
bz1110110 .
1-
0,
1+
0*
b1001 )
bz110 (
b1111 '
b1010 &
b1111 %
0$
b1010 #
b1001 "
1!
$end
#5000
13
bz0101101 4
b1010 "
b1010 )
0-
12
bz111 (
1,
bz1010111 .
1$
#15000
13
1>
1-
b1111 "
b1111 )
19
02
0=
0,
07
bz1110110 :
08
bz000 (
01
0!
bz0101111 .
bz1111010 4
bz1110110 ?
0+
00
0;
b1100 %
b1100 '
b10 #
b10 &
#30000
b1110 "
b1110 )
0-
bz1101111 .
0$
#50000
1-
b1011 "
b1011 )
09
bz1110110 .
bz1101111 :
bz1111010 ?
1+
06
0<
1;
b1 %
b1 '
b1010 #
b1010 &
#75000
19
bz0101111 :
03
18
11
bz1011011 4
b1100 "
b1100 )
0-
12
bz011 (
1,
bz1010111 .
1$
#105000
b1110 "
b1110 )
13
bz0101101 4
10
b11 %
b11 '
#155000
03
bz1101101 4
b1101 "
b1101 )
1-
02
bz010 (
0,
bz1110110 .
0$
