fad.v
`timescale 1ns/1ps
module adder(a,b,ci,s,c1);
	input a,b,ci;
	output s,c1;
	wire [7:0] c;
	nand(c[1],a,b);
	nand(c[2],c[1],a);
	nand(c[3],c[1],b);
	nand(c[4],c[2],c[3]);
	nand(c[5],c[4],ci);
	nand(c[0],c[4],c[5]);
	nand(c[6],c[5],ci);
	nand(s,c[6],c[0]);
	nand(c1,c[1],c[5]);
endmodule

fadd_t.v
`timescale 1ns/1ps
module testbench2;
	reg a,x,c;
	wire y,z;
	adder g1(a,x,c,y,z);
	initial
		begin
			$dumpfile("fadder.vcd");
			$dumpvars;
			$monitor(,$time," a=%b, x=%b,c=%b, y=%b,z=%b",a,x,c,y,z);
			#0 a=1'b0;x=1'b0;c=1'b0;
			#5 c=1'b1;
			#10 a=1'b1;x=1'b0;
			#15 c = 1'b0;
			#20 a=1'b0;x=1'b1;
			#25 c=1'b1;
			#30 a=1'b1;x=1'b1;
			#50 c=1'b0;
			#100 $finish;
		end
endmodule

hadder.vcd
$date
	Tue Aug 29 15:50:17 2017
$end
$version
	Icarus Verilog
$end
$timescale
	1ps
$end
$scope module testbench2 $end
$var wire 1 ! z $end
$var wire 1 " y $end
$var reg 1 # a $end
$var reg 1 $ c $end
$var reg 1 % x $end
$scope module g1 $end
$var wire 1 # a $end
$var wire 1 % b $end
$var wire 1 ! c1 $end
$var wire 1 $ ci $end
$var wire 1 " s $end
$var wire 8 & c [7:0] $end
$upscope $end
$upscope $end
$enddefinitions $end
#0
$dumpvars
bz1101111 &
0%
0$
0#
0"
0!
$end
#5000
1"
bz0101111 &
1$
#15000
0"
1!
bz1011011 &
1#
#30000
1"
0!
bz1111010 &
0$
#50000
bz1110110 &
1%
0#
#75000
0"
1!
bz1010111 &
1$
#105000
1"
bz0101101 &
1#
#155000
0"
bz1101101 &
0$
